{
  "nodes": [
    {
      "id": "7c38e0aa-d9ff-4706-87d7-5e5c6adfe4ee",
      "type": "text-area",
      "initialized": false,
      "position": {
        "x": -230.9283190229295,
        "y": 13.290838504916806
      },
      "data": {
        "label": "Start",
        "body": "<p>Let's get this show on the road. Here are your choices:</p>",
        "components": [
          "f5a75c48-2a99-41f4-89de-368f49ac6bed"
        ],
        "isStartingNode": true
      },
      "style": {
        "width": "300px",
        "height": "300px"
      },
      "class": ""
    },
    {
      "id": "1a11f905-3879-402c-9a32-05ac88d094dc",
      "type": "text-field",
      "initialized": false,
      "position": {
        "x": 290.988004760684,
        "y": 4.984064439343808
      },
      "data": {
        "label": "Whoosh! Text field!"
      },
      "style": {
        "width": "220px",
        "height": "50px"
      },
      "class": ""
    },
    {
      "id": "ec06743f-ddf2-4c54-9c78-e4abc8a39404",
      "type": "text-area",
      "initialized": false,
      "position": {
        "x": 1049.677854480052,
        "y": -116.66038802586974
      },
      "data": {
        "label": "Node 3",
        "body": "<p>And that's it! This is the end! Try another response!</p>"
      },
      "style": {
        "width": "304px",
        "height": "300px"
      },
      "class": ""
    },
    {
      "id": "9ccd8c79-9639-4ef5-8cd9-21f432b04b6d",
      "type": "note",
      "initialized": false,
      "position": {
        "x": 569.3217648708064,
        "y": 385.6326491618078
      },
      "data": {
        "label": "Welcome to Corkboard!",
        "body": "<p><strong><em>Getting Started:</em></strong></p><ol><li>Right click the background to bring up the context menu</li><li>Double click nodes to delete and modify them</li><li>Drag attribute nodes over text area nodes to combine them</li><li>Save &amp; load projects using the toolbar in the upper-left</li></ol>"
      },
      "style": {
        "width": "784px",
        "height": "269px"
      },
      "class": ""
    },
    {
      "id": "f5a75c48-2a99-41f4-89de-368f49ac6bed",
      "type": "component",
      "initialized": false,
      "position": {
        "x": -314.86993697223653,
        "y": 364.88110586289486
      },
      "data": {
        "label": "Conelle",
        "attributes": [
          "content/portraits/conelle/Portrait_Connelle.png",
          "Portrait"
        ]
      },
      "class": ""
    },
    {
      "id": "bcd87f9c-68a2-4765-b4e8-36cd1a543bab",
      "type": "text-area",
      "initialized": false,
      "position": {
        "x": 572.9082130977682,
        "y": 66.81252906311596
      },
      "data": {
        "label": "Code Node",
        "body": "<p>This node contains code that will add a White Gold Trinket to the player's inventory.</p><p><br></p><p><code>Player:addItemToInventory(\"#WhiteGoldTrinket\", 1);</code></p><p><br></p><p><br></p>"
      },
      "style": {
        "width": "413px",
        "height": "300px"
      },
      "class": ""
    },
    {
      "id": "7712bd45-553f-437f-88ba-8e9ec4af6251",
      "type": "text-area",
      "initialized": false,
      "position": {
        "x": 208.63415079156593,
        "y": 355.2830634885622
      },
      "data": {
        "label": "Node 4",
        "body": "<p>You drive by some really beautiful mountains on the way to the coding node.</p>"
      },
      "style": {
        "width": "300px",
        "height": "300px"
      },
      "class": ""
    }
  ],
  "edges": [
    {
      "id": "5ef9e938-bc8d-4e93-b017-247022fbab2e",
      "type": "default",
      "source": "7c38e0aa-d9ff-4706-87d7-5e5c6adfe4ee",
      "target": "1a11f905-3879-402c-9a32-05ac88d094dc",
      "updatable": true,
      "data": {},
      "label": "Dialogue Choice",
      "sourceX": 71.57185413772635,
      "sourceY": 163.2909055918944,
      "targetX": 288.4879602739869,
      "targetY": 29.984084070599643
    },
    {
      "id": "9e5b2df1-dc66-415b-a265-4624011d2851",
      "type": "default",
      "source": "1a11f905-3879-402c-9a32-05ac88d094dc",
      "target": "ec06743f-ddf2-4c54-9c78-e4abc8a39404",
      "updatable": true,
      "data": {},
      "label": "What?! Nothing happened?!",
      "sourceX": 513.4882246631978,
      "sourceY": 29.984084070599643,
      "targetX": 1047.177809993355,
      "targetY": 33.33967906110786
    },
    {
      "id": "vueflow__edge-7c38e0aa-d9ff-4706-87d7-5e5c6adfe4ee-bcd87f9c-68a2-4765-b4e8-36cd1a543bab",
      "type": "default",
      "source": "7c38e0aa-d9ff-4706-87d7-5e5c6adfe4ee",
      "target": "bcd87f9c-68a2-4765-b4e8-36cd1a543bab",
      "sourceHandle": null,
      "targetHandle": null,
      "data": {},
      "label": "Code Choice",
      "sourceX": 71.57185413772635,
      "sourceY": 163.2909055918944,
      "targetX": 570.4080672099562,
      "targetY": 216.81254544953612
    },
    {
      "id": "vueflow__edge-7712bd45-553f-437f-88ba-8e9ec4af6251-bcd87f9c-68a2-4765-b4e8-36cd1a543bab",
      "type": "default",
      "source": "7712bd45-553f-437f-88ba-8e9ec4af6251",
      "target": "bcd87f9c-68a2-4765-b4e8-36cd1a543bab",
      "sourceHandle": null,
      "targetHandle": null,
      "data": {},
      "label": "",
      "sourceX": 511.13437465277923,
      "sourceY": 505.2830798749824,
      "targetX": 570.4080672099562,
      "targetY": 216.81254544953612
    },
    {
      "id": "vueflow__edge-bcd87f9c-68a2-4765-b4e8-36cd1a543bab-ec06743f-ddf2-4c54-9c78-e4abc8a39404",
      "type": "default",
      "source": "bcd87f9c-68a2-4765-b4e8-36cd1a543bab",
      "target": "ec06743f-ddf2-4c54-9c78-e4abc8a39404",
      "sourceHandle": null,
      "targetHandle": null,
      "data": {},
      "label": "",
      "sourceX": 988.4083183342789,
      "sourceY": 216.81254544953612,
      "targetX": 1047.177809993355,
      "targetY": 33.33967906110786
    },
    {
      "id": "vueflow__edge-7c38e0aa-d9ff-4706-87d7-5e5c6adfe4ee-7712bd45-553f-437f-88ba-8e9ec4af6251",
      "type": "default",
      "source": "7c38e0aa-d9ff-4706-87d7-5e5c6adfe4ee",
      "target": "7712bd45-553f-437f-88ba-8e9ec4af6251",
      "sourceHandle": null,
      "targetHandle": null,
      "data": {},
      "label": "Scenic Route",
      "sourceX": 71.57185413772635,
      "sourceY": 163.2909055918944,
      "targetX": 206.13420770598367,
      "targetY": 505.2830798749824
    }
  ],
  "position": [
    451.5615800533802,
    315.47554027999206
  ],
  "zoom": 1.0480007719291116,
  "viewport": {
    "x": 451.5615800533802,
    "y": 315.47554027999206,
    "zoom": 1.0480007719291116
  }
}